{
    "the": 100, "be": 90, "to": 80, "of": 70, "and": 60,
    "a": 50, "in": 40, "that": 30, "have": 20, "i": 10,
    "it": 45, "for": 35, "not": 25, "on": 15, "with": 5,
    "he": 48, "as": 38, "you": 28, "do": 18, "at": 8,
    "this": 43, "but": 33, "his": 23, "by": 13, "from": 3,
    "they": 47, "we": 37, "say": 27, "her": 17, "she": 7,
    "or": 42, "an": 32, "will": 22, "my": 12, "one": 2,
    "all": 46, "would": 36, "there": 26, "their": 16, "what": 6,
    "so": 41, "up": 31, "out": 21, "if": 11, "about": 1,
    "who": 44, "get": "34", "which": 24, "go": 14, "me": 4,
    "when": 49, "make": 39, "can": 29, "like": 19, "time": 9,
    "just": 43, "him": 33, "know": 23, "take": 13, "people": 3,
    "into": 47, "year": 37, "your": 27, "good": 17, "some": 7,
    "could": 42, "them": 32, "see": 22, "other": 12, "than": 2,
    "then": 46, "now": 36, "look": 26, "only": 16, "come": 6,
    "its": 41, "over": 31, "think": 21, "also": 11, "back": 1
}
